aiia_django_rest_swagger/__init__.py
aiia_django_rest_swagger/renderers.py
aiia_django_rest_swagger/settings.py
aiia_django_rest_swagger/views.py
aiia_django_rest_swagger/static/aiia_django_rest_swagger/favicon-16x16.png
aiia_django_rest_swagger/static/aiia_django_rest_swagger/favicon-32x32.png
aiia_django_rest_swagger/static/aiia_django_rest_swagger/logo_small.png
aiia_django_rest_swagger/static/aiia_django_rest_swagger/bundles/app.bundle.css
aiia_django_rest_swagger/static/aiia_django_rest_swagger/bundles/app.bundle.js
aiia_django_rest_swagger/static/aiia_django_rest_swagger/bundles/vendors.bundle.css
aiia_django_rest_swagger/static/aiia_django_rest_swagger/bundles/vendors.bundle.js
aiia_django_rest_swagger/templates/aiia_django_rest_swagger/index.html
aiia_django_rest_swagger-1.0.0.dist-info/LICENSE
aiia_django_rest_swagger-1.0.0.dist-info/METADATA
aiia_django_rest_swagger-1.0.0.dist-info/WHEEL
aiia_django_rest_swagger-1.0.0.dist-info/top_level.txt
aiia_django_rest_swagger-1.0.0.dist-info/RECORD
